google_searching.py
google_searching-0.8.1.dist-info/LICENSE
google_searching-0.8.1.dist-info/METADATA
google_searching-0.8.1.dist-info/WHEEL
google_searching-0.8.1.dist-info/top_level.txt
google_searching-0.8.1.dist-info/RECORD
